Workbook
Name Slicer_Date: #N/A
Name Slicer_Industry: #N/A

Sheet Meetings
A1: Date | B1: Customer | C1: Discussion Summary | D1: Action Items | E1: Owner | F1: Due Date
A2: 45662 | B2: Alpha Corp | C2: Initial discovery call | D2: Send product brochure | E2: Owner 1 | F2: 45667
A3: 45669 | B3: Beta Ltd | C3: Demo presented | D3: Share pricing deck | E3: Owner 2 | F3: 45674
A4: 45677 | B4: Gamma Inc | C4: Requirements gathering | D4: Draft proposal | E4: Owner 1 | F4: 45684
A5: 45691 | B5: Delta Pvt | C5: Contract negotiation | D5: Legal review | E5: Owner 3 | F5: 45698
A6: 45702 | B6: Epsilon Co | C6: Technical deep-dive | D6: POC setup | E6: Owner 2 | F6: 45709
A7: 45713 | B7: Zeta Systems | C7: Exec stakeholder meeting | D7: ROI analysis | E7: Owner 1 | F7: 45720
A8: 45722 | B8: Eta Partners | C8: Budget discussion | D8: Revise quote | E8: Owner 3 | F8: 45729
A9: 45734 | B9: Theta Corp | C9: Final proposal review | D9: Sign contract | E9: Owner 2 | F9: 45741
A10: 45748 | B10: Iota Ltd | C10: Onboarding kickoff | D10: Share timeline | E10: Owner 1 | F10: 45755
A11: 45762 | B11: Kappa Inc | C11: Quarterly business review | D11: Follow up tasks | E11: Owner 3 | F11: 45769

Sheet Partners
A1: Partner Name | B1: Region | C1: Contact | D1: Opportunity Count | E1: Pipeline Value | F1: Status
A2: SecureTech Solutions | B2: North | C2: Raj Sharma | D2: 66 | E2: 4500000 | F2: Active
A3: CyberGuard Systems | B3: West | C3: Amit Patel | D3: 18 | E3: 7200000 | F3: Active
A4: DataShield Partners | B4: South | C4: Priya Nair | D4: 10 | E4: 3800000 | F4: Active
A5: NetSecure Consulting | B5: East | C5: Sandeep Roy | D5: 6 | E5: 1800000 | F5: Prospect
A6: InfoProtect Technologies | B6: North | C6: Mohit Verma | D6: 14 | E6: 5500000 | F6: Active
A7: DLP Experts Pvt Ltd | B7: West | C7: Kunal Shah | D7: 20 | E7: 8500000 | F7: Active
A8: CloudDefend Solutions | B8: South | C8: Akash Reddy | D8: 9 | E8: 2900000 | F8: Inactive
A9: SecureWave Technologies | B9: East | C9: Ankit Das | D9: 11 | E9: 3400000 | F9: Active
A10: CyberSphere Partners | B10: North | C10: Rohit Gupta | D10: 15 | E10: 6200000 | F10: Active
A11: TrustShield Systems | B11: West | C11: Vivek Mehta | D11: 7 | E11: 2100000 | F11: Prospect
A12: DataArmor Consulting | B12: South | C12: Deepak Kumar | D12: 16 | E12: 6800000 | F12: Active
A13: Sentinel Technologies | B13: East | C13: Arjun Sen | D13: 8 | E13: 2500000 | F13: Inactive
... A21: RiskShield Solutions | B21: East | C21: Sumit Dutta | D21: 9 | E21: 2800000 | F21: Inactive

Sheet Forecast
A1: Month | B1: Pipeline Value | C1: Weighted Pipeline | D1: Closed Won | E1: Target | F1: Achievement %
A2: Jan | B2: 200000 | C2: 120000 | D2: 60000 | E2: 160000 | F2: =IFERROR(D2/E2*100,0) -> 37.5
A3: Feb | B3: 320000 | C3: 190000 | D3: 95000 | E3: 250000 | F3: =IFERROR(D3/E3*100,0) -> 38
A4: Mar | B4: 410000 | C4: 250000 | D4: 130000 | E4: 320000 | F4: =IFERROR(D4/E4*100,0) -> 40.625
A5: Apr | B5: 500000 | C5: 310000 | D5: 170000 | E5: 400000 | F5: =IFERROR(D5/E5*100,0) -> 42.5
A6: May | B6: 620000 | C6: 380000 | D6: 220000 | E6: 490000 | F6: =IFERROR(D6/E6*100,0) -> 44.897959
A7: Jun | B7: 700000 | C7: 430000 | D7: 260000 | E7: 560000 | F7: =IFERROR(D7/E7*100,0) -> 46.428571
A8: Jul | B8: 810000 | C8: 500000 | D8: 300000 | E8: 640000 | F8: =IFERROR(D8/E8*100,0) -> 46.875
A9: Aug | B9: 890000 | C9: 550000 | D9: 340000 | E9: 710000 | F9: =IFERROR(D9/E9*100,0) -> 47.887324
A10: Sep | B10: 970000 | C10: 610000 | D10: 390000 | E10: 780000 | F10: =IFERROR(D10/E10*100,0) -> 50
A11: Oct | B11: 1050000 | C11: 660000 | D11: 430000 | E11: 840000 | F11: =IFERROR(D11/E11*100,0) -> 51.190476

Sheet Pipeline
A1: Opportunity ID | B1: Customer Name | C1: Industry | D1: Country | E1: Contact Person | F1: Lead Source | G1: Opportunity Value | H1: Stage | I1: Probability % | J1: Weighted Pipeline | K1: Expected Close Date | L1: Competitor | M1: Next Action | N1: Sales Owner | O1: Status
A2: OPP001 | B2: Alpha Corp | C2: IT | D2: India | E2: Rajan M | F2: Website | G2: 120000 | H2: Proposal | I2: 65 | J2: 200000 | L2: Demo | O2: Open
A3: OPP002 | B3: Beta Ltd | C3: Finance | D3: UAE | E3: Sara K | F3: Referral | G3: 250000 | H3: Negotiation | I3: 80 | J3: 200000 | L3: Follow Up | O3: Open
A4: OPP003 | B4: Gamma Inc | C4: Manufacturing | D4: USA | E4: John P | F4: Event | G4: 85000 | H4: Prospecting | I4: 30 | J4: 200000 | L4: Send Deck | O4: Closed Won
A5: OPP004 | B5: Delta Pvt | C5: Retail | D5: India | E5: Priya S | F5: LinkedIn | G5: 310000 | H5: Closed Won | I5: 95 | J5: 1000003 | L5: Invoice | O5: Closed Won
A6: OPP005 | B6: Epsilon Co | C6: IT | D6: UK | E6: Mark D | F6: Website | G6: 175000 | H6: Proposal | I6: 55 | J6: 1000003 | L6: Demo | O6: Open
A7: OPP006 | B7: Zeta Systems | C7: Healthcare | D7: India | E7: Anita R | F7: Event | G7: 420000 | H7: Negotiation | I7: 75 | J7: 1000003 | L7: Contract | O7: Open
A8: OPP007 | B8: Eta Partners | C8: IT | D8: UAE | E8: Fahad A | F8: Referral | G8: 95000 | H8: Prospecting | I8: 25 | J8: 1000003 | L8: Discovery | O8: Open
A9: OPP008 | B9: Theta Corp | C9: Finance | D9: USA | E9: Lisa N | F9: LinkedIn | G9: 540000 | H9: Closed Won | I9: 90 | J9: 1000003 | L9: Handover | O9: Closed Won
A10: OPP009 | B10: Iota Ltd | C10: Manufacturing | D10: India | E10: Suresh V | F10: Website | G10: 230000 | H10: Proposal | I10: 60 | J10: 1000003 | L10: Follow Up | O10: Open
A11: OPP010 | B11: Kappa Inc | C11: Retail | D11: UK | E11: Emma B | F11: Event | G11: 390000 | H11: Negotiation | I11: 70 | J11: 1000003 | L11: Negotiation | O11: Open
A12: Opp11 | B12: Prakhar | C12: IT | D12: India | E12: PK | F12: Event | G12: 10000000 | H12: Proposal | I12: 80 | J12: 1000003

Sheet CRM
A1: DLP SALES CRM | ANALYTICS DASHBOARD
A3: ▌ PIPELINE ANALYSIS
A27: ▌ MEETINGS INSIGHTS
A49: ▌ FORECAST TRENDS
A83: ▌ PARTNERS OVERVIEW
A113: ▌ DASHBOARD KPI SUMMARY

Sheet Pivot
A1: Countrywise Opportunity Value | J1: Competitorwise Probability
A2: Country | B2: Opportunity Value | D2: Sum of Pipeline Value | E2: Column Labels | J2: Competitor | K2: Probability %
A3: India | B3: 310000 | D3: Row Labels | E3: Active | F3: Inactive | G3: Prospect | H3: Grand Total | J3: Invoice | K3: 95
A4: UK | B4: 390000 | D4: CloudDefend Solutions | F4: 2900000 | H4: 2900000 | J4: Negotiation | K4: 70
A5: Grand Total | B5: 700000 | D5: CyberGuard Systems | E5: 7200000 | H5: 7200000 | J5: Grand Total | K5: 165
D6: CyberMatrix Consulting | E6: 9100000 | H6: 9100000
D7: CyberSphere Partners | E7: 6200000 | H7: 6200000
D8: DataArmor Consulting | E8: 6800000 | H8: 6800000
A9: Contactwise Opportunity Value | D9: DataLock Technologies | E9: 4700000 | H9: 4700000
A10: Contact Person | B10: Opportunity Value | D10: DataShield Partners | E10: 3800000 | H10: 3800000
A11: Emma B | B11: 390000 | D11: DLP Experts Pvt Ltd | E11: 8500000 | H11: 8500000
A12: Priya S | B12: 310000 | D12: Fortress Cyber Systems | E12: 7900000 | H12: 7900000
A13: Grand Total | B13: 700000 | D13: InfoProtect Technologies | E13: 5500000 | H13: 5500000
D14: InfoSec Associates | E14: 4900000 | H14: 4900000
D15: NetSecure Consulting | G15: 1800000 | H15: 1800000
D16: RiskShield Solutions | F16: 2800000 | H16: 2800000
D17: SafeNet Solutions | E17: 7300000 | H17: 7300000
D18: SecureLink Partners | E18: 3200000 | H18: 3200000
D19: SecureTech Solutions | E19: 4500000 | H19: 4500000
D20: SecureWave Technologies | E20: 3400000 | H20: 3400000
D21: Sentinel Technologies | F21: 2500000 | H21: 2500000
D22: ShieldCore Technologies | G22: 1600000 | H22: 1600000
D23: TrustShield Systems | G23: 2100000 | H23: 2100000
D24: Grand Total | E24: 83000000 | F24: 8200000 | G24: 5500000 | H24: 96700000
A26: Customerwise Owner %
A27: Count of Action Items | B27: Column Labels
A28: Row Labels | B28: Owner 1 | C28: Owner 2 | D28: Owner 3 | E28: Grand Total
A29: Alpha Corp | B29: 0.1 | C29: 0 | D29: 0 | E29: 0.1
A30: Beta Ltd | B30: 0 | C30: 0.1 | D30: 0 | E30: 0.1
A31: Delta Pvt | B31: 0 | C31: 0 | D31: 0.1 | E31: 0.1
A32: Epsilon Co | B32: 0 | C32: 0.1 | D32: 0 | E32: 0.1
A33: Eta Partners | B33: 0 | C33: 0 | D33: 0.1 | E33: 0.1
A34: Gamma Inc | B34: 0.1 | C34: 0 | D34: 0 | E34: 0.1
A35: Iota Ltd | B35: 0.1 | C35: 0 | D35: 0 | E35: 0.1
A36: Kappa Inc | B36: 0 | C36: 0 | D36: 0.1 | E36: 0.1
A37: Theta Corp | B37: 0 | C37: 0.1 | D37: 0 | E37: 0.1
A38: Zeta Systems | B38: 0.1 | C38: 0 | D38: 0 | E38: 0.1
A39: Grand Total | B39: 0.4 | C39: 0.3 | D39: 0.3 | E39: 1

Sheet Dashboard

Sheet _AggData
A1: Country | B1: Weighted Pipeline | C1: Opportunity Value | E1: Status | F1: Count | H1: Month | I1: Meeting Count | K1: Owner | L1: Meetings | N1: Region | O1: Pipeline Value | P1: Opp Count | R1: Status | S1: Count | U1: KPI | V1: Value
A2: India | B2: =SUMIF(Pipeline!D:D,A2,Pipeline!J:J) -> 4200012 | C2: =SUMIF(Pipeline!D:D,A2,Pipeline!G:G) -> 11080000 | E2: Open | F2: =COUNTIF(Pipeline!O:O,"Open") -> 7 | H2: Jan | I2: =COUNTIF(Meetings!A:A,">="&DATE(2025,1,1))-COUNTIF(Meetings!A:A,">="&DATE(2025,2,1)) -> 3 | K2: Owner 1 | L2: =COUNTIF(Meetings!E:E,K2) -> 4 | N2: North | O2: =SUMIF(Partners!B:B,N2,Partners!E:E) -> 24300000 | P2: =SUMIF(Partners!B:B,N2,Partners!D:D) -> 118 | R2: Active | S2: =COUNTIF(Partners!F:F,"Active") -> 14 | U2: Total Pipeline | V2: =SUM(Pipeline!G:G) -> 12615000
A3: UAE | B3: =SUMIF(Pipeline!D:D,A3,Pipeline!J:J) -> 1200003 | C3: =SUMIF(Pipeline!D:D,A3,Pipeline!G:G) -> 345000 | E3: Closed Won | F3: =COUNTIF(Pipeline!O:O,"Closed Won") -> 3 | H3: Feb | I3: =COUNTIF(Meetings!A:A,">="&DATE(2025,2,1))-COUNTIF(Meetings!A:A,">="&DATE(2025,3,1)) -> 3 | K3: Owner 2 | L3: =COUNTIF(Meetings!E:E,K3) -> 3 | N3: South | O3: =SUMIF(Partners!B:B,N3,Partners!E:E) -> 19800000 | P3: =SUMIF(Partners!B:B,N3,Partners!D:D) -> 52 | R3: Inactive | S3: =COUNTIF(Partners!F:F,"Inactive") -> 3 | U3: Weighted Pipeline | V3: =SUM(Pipeline!J:J) -> 8600024
A4: USA | B4: =SUMIF(Pipeline!D:D,A4,Pipeline!J:J) -> 1200003 | C4: =SUMIF(Pipeline!D:D,A4,Pipeline!G:G) -> 625000 | E4: Closed Lost | F4: =COUNTIF(Pipeline!O:O,"Closed Lost") -> 0 | H4: Mar | I4: =COUNTIF(Meetings!A:A,">="&DATE(2025,3,1))-COUNTIF(Meetings!A:A,">="&DATE(2025,4,1)) -> 2 | K4: Owner 3 | L4: =COUNTIF(Meetings!E:E,K4) -> 3 | N4: East | O4: =SUMIF(Partners!B:B,N4,Partners!E:E) -> 18400000 | P4: =SUMIF(Partners!B:B,N4,Partners!D:D) -> 53 | R4: Prospect | S4: =COUNTIF(Partners!F:F,"Prospect") -> 3 | U4: Closed Won | V4: =SUMIF(Pipeline!O:O,"Closed Won",Pipeline!G:G) -> 935000
A5: UK | B5: =SUMIF(Pipeline!D:D,A5,Pipeline!J:J) -> 2000006 | C5: =SUMIF(Pipeline!D:D,A5,Pipeline!G:G) -> 565000 | H5: Apr | I5: =COUNTIF(Meetings!A:A,">="&DATE(2025,4,1))-COUNTIF(Meetings!A:A,">="&DATE(2025,5,1)) -> 2 | N5: West | O5: =SUMIF(Partners!B:B,N5,Partners!E:E) -> 34200000 | P5: =SUMIF(Partners!B:B,N5,Partners!D:D) -> 83 | U5: Open Deals Value | V5: =SUMIF(Pipeline!O:O,"Open",Pipeline!G:G) -> 1680000
A6: Germany | B6: =SUMIF(Pipeline!D:D,A6,Pipeline!J:J) -> 0 | C6: =SUMIF(Pipeline!D:D,A6,Pipeline!G:G) -> 0 | H6: May | I6: =COUNTIF(Meetings!A:A,">="&DATE(2025,5,1))-COUNTIF(Meetings!A:A,">="&DATE(2025,6,1)) -> 0 | U6: Total Forecast | V6: =SUM(Forecast!B:B) -> 6470000
H7: Jun | I7: =COUNTIF(Meetings!A:A,">="&DATE(2025,6,1))-COUNTIF(Meetings!A:A,">="&DATE(2025,7,1)) -> 0
H8: Jul | I8: =COUNTIF(Meetings!A:A,">="&DATE(2025,7,1))-COUNTIF(Meetings!A:A,">="&DATE(2025,8,1)) -> 0
H9: Aug | I9: =COUNTIF(Meetings!A:A,">="&DATE(2025,8,1))-COUNTIF(Meetings!A:A,">="&DATE(2025,9,1)) -> 0
H10: Sep | I10: =COUNTIF(Meetings!A:A,">="&DATE(2025,9,1))-COUNTIF(Meetings!A:A,">="&DATE(2025,10,1)) -> 0
H11: Oct | I11: =COUNTIF(Meetings!A:A,">="&DATE(2025,10,1))-COUNTIF(Meetings!A:A,">="&DATE(2025,11,1)) -> 0
H12: Nov | I12: =COUNTIF(Meetings!A:A,">="&DATE(2025,11,1))-COUNTIF(Meetings!A:A,">="&DATE(2025,12,1)) -> 0
H13: Dec | I13: =COUNTIF(Meetings!A:A,">="&DATE(2025,12,1))-COUNTIF(Meetings!A:A,">="&DATE(2025,13,1)) -> 0
